pulumi_confluentcloud/__init__.py
pulumi_confluentcloud/_inputs.py
pulumi_confluentcloud/_utilities.py
pulumi_confluentcloud/access_point.py
pulumi_confluentcloud/api_key.py
pulumi_confluentcloud/business_metadata.py
pulumi_confluentcloud/business_metadata_binding.py
pulumi_confluentcloud/byok_key.py
pulumi_confluentcloud/catalog_entity_attributes.py
pulumi_confluentcloud/catalog_integration.py
pulumi_confluentcloud/certificate_authority.py
pulumi_confluentcloud/certificate_pool.py
pulumi_confluentcloud/cluster_link.py
pulumi_confluentcloud/connect_artifact.py
pulumi_confluentcloud/connector.py
pulumi_confluentcloud/custom_connector_plugin.py
pulumi_confluentcloud/custom_connector_plugin_version.py
pulumi_confluentcloud/dns_forwarder.py
pulumi_confluentcloud/dns_record.py
pulumi_confluentcloud/environment.py
pulumi_confluentcloud/flink_artifact.py
pulumi_confluentcloud/flink_compute_pool.py
pulumi_confluentcloud/flink_connection.py
pulumi_confluentcloud/flink_statement.py
pulumi_confluentcloud/gateway.py
pulumi_confluentcloud/get_access_point.py
pulumi_confluentcloud/get_business_metadata.py
pulumi_confluentcloud/get_business_metadata_binding.py
pulumi_confluentcloud/get_byok_key.py
pulumi_confluentcloud/get_catalog_integration.py
pulumi_confluentcloud/get_certificate_authority.py
pulumi_confluentcloud/get_certificate_pool.py
pulumi_confluentcloud/get_cluster_link.py
pulumi_confluentcloud/get_connect_artifact.py
pulumi_confluentcloud/get_dns_record.py
pulumi_confluentcloud/get_environment.py
pulumi_confluentcloud/get_environments.py
pulumi_confluentcloud/get_flink_artifact.py
pulumi_confluentcloud/get_flink_compute_pool.py
pulumi_confluentcloud/get_flink_connection.py
pulumi_confluentcloud/get_flink_region.py
pulumi_confluentcloud/get_gateway.py
pulumi_confluentcloud/get_group_mapping.py
pulumi_confluentcloud/get_identity_pool.py
pulumi_confluentcloud/get_identity_provider.py
pulumi_confluentcloud/get_invitation.py
pulumi_confluentcloud/get_ip_addresses.py
pulumi_confluentcloud-2.54.0.dist-info/METADATA
pulumi_confluentcloud-2.54.0.dist-info/WHEEL
pulumi_confluentcloud-2.54.0.dist-info/top_level.txt
pulumi_confluentcloud-2.54.0.dist-info/RECORD
